gitapi/gitapi.py
gitapi/testgitapi.py
gitapi/__init__.py
gitapi-1.1.0a2.dist-info/top_level.txt
gitapi-1.1.0a2.dist-info/DESCRIPTION.rst
gitapi-1.1.0a2.dist-info/METADATA
gitapi-1.1.0a2.dist-info/metadata.json
gitapi-1.1.0a2.dist-info/RECORD
gitapi-1.1.0a2.dist-info/WHEEL
