Metadata-Version: 2.0
Name: gitapi
Version: 1.1.0a2
Summary: Python API to Git using the command-line interface
Home-page: https://bitbucket.org/haard/gitapi
Author: Fredrik Håård
Author-email: fredrik@metallapan.se
License: Do whatever you want, don't blame me
Keywords: git api
Platform: UNKNOWN
